cmdcall.py
cmdcall-0.0.1.dist-info/LICENSE
cmdcall-0.0.1.dist-info/METADATA
cmdcall-0.0.1.dist-info/WHEEL
cmdcall-0.0.1.dist-info/top_level.txt
cmdcall-0.0.1.dist-info/RECORD
