Metadata-Version: 2.1
Name: cmdcall
Version: 0.0.1
Summary: Utility for quick test python script
Home-page: https://github.com/xudifsd/cmdcall
Author: Di Xu
Author-email: xudifsd@gmail.com
License: UNKNOWN
Platform: UNKNOWN
Classifier: Programming Language :: Python :: 2.7
Classifier: License :: OSI Approved :: MIT License
Classifier: Operating System :: OS Independent
